devtools_punycode/__init__.py
devtools_punycode-1.0.1.dist-info/METADATA
devtools_punycode-1.0.1.dist-info/WHEEL
devtools_punycode-1.0.1.dist-info/top_level.txt
devtools_punycode-1.0.1.dist-info/RECORD
