Metadata-Version: 2.1
Name: devtools-punycode
Version: 1.0.1
Summary: Punycode encoder/decoder
Home-page: https://devtools.at/tools/punycode
Author: DevTools.at
Author-email: hello@devtools.at
Project-URL: Homepage, https://devtools.at/tools/punycode
Project-URL: Repository, https://github.com/devtools-at/punycode
Classifier: Development Status :: 4 - Beta
Classifier: Intended Audience :: Developers
Classifier: License :: OSI Approved :: MIT License
Classifier: Programming Language :: Python :: 3
Requires-Python: >=3.8
